ghas_cli/__init__.py
ghas_cli/utils/__init__.py
ghas_cli/utils/actions.py
ghas_cli/utils/dependabot.py
ghas_cli/utils/export.py
ghas_cli/utils/issues.py
ghas_cli/utils/network.py
ghas_cli/utils/repositories.py
ghas_cli/utils/roles.py
ghas_cli/utils/secrets.py
ghas_cli/utils/teams.py
ghas_cli/utils/vulns.py
ghas_cli-1.7.3.data/data/codeql-analysis-default.yml
ghas_cli-1.7.3.data/data/codeql-config-default.yml
ghas_cli-1.7.3.data/data/codeql.md
ghas_cli-1.7.3.data/data/dependabot.md
ghas_cli-1.7.3.data/data/dependency_enforcement.yml
ghas_cli-1.7.3.data/data/secret_scanner.md
ghas_cli-1.7.3.data/data/secret_scanner_push_protection.md
ghas_cli-1.7.3.dist-info/WHEEL
ghas_cli-1.7.3.dist-info/entry_points.txt
ghas_cli-1.7.3.dist-info/METADATA
ghas_cli-1.7.3.dist-info/RECORD
