Metadata-Version: 2.4
Name: ghas-cli
Version: 1.7.3
Summary: Command line interface to interact with GitHub Advanced Security.
Keywords: security,cli,github,utility
Author: jboursier
Author-email: jboursier <jboursier@malwarebytes.com>
License-Expression: MIT
Classifier: Development Status :: 5 - Production/Stable
Classifier: Environment :: Console
Classifier: Intended Audience :: Developers
Classifier: Intended Audience :: Information Technology
Classifier: Natural Language :: English
Classifier: Operating System :: OS Independent
Classifier: Topic :: Utilities
Classifier: Programming Language :: Python
Classifier: Programming Language :: Python :: 3 :: Only
Classifier: Programming Language :: Python :: 3.8
Classifier: Programming Language :: Python :: 3.9
Classifier: Programming Language :: Python :: 3.10
Classifier: Programming Language :: Python :: 3.11
Classifier: Programming Language :: Python :: 3.12
Classifier: Programming Language :: Python :: 3.13
Classifier: Programming Language :: Python :: 3.14
Requires-Dist: click>=8.1.8
Requires-Dist: configparser>=7.1.0
Requires-Dist: python-magic>=0.4.27
Requires-Dist: requests>=2.32.3
Requires-Dist: urllib3>=2.2.3
Requires-Dist: ruff>=0.11.2 ; extra == 'dev'
Requires-Python: >=3.8
Project-URL: Changelog, https://github.com/Malwarebytes/ghas-cli/releases
Project-URL: Documentation, https://github.com/Malwarebytes/ghas-cli/wiki
Project-URL: Homepage, https://github.com/Malwarebytes/ghas-cli
Project-URL: Issues, https://github.com/Malwarebytes/ghas-cli/issues
Project-URL: Repository, https://github.com/Malwarebytes/ghas-cli
Project-URL: funding, https://www.malwarebytes.com/
Provides-Extra: dev
